PilAnimate/__init__.py
PilAnimate-0.4.1.dist-info/LICENSE
PilAnimate-0.4.1.dist-info/METADATA
PilAnimate-0.4.1.dist-info/WHEEL
PilAnimate-0.4.1.dist-info/top_level.txt
PilAnimate-0.4.1.dist-info/RECORD
